[
  {
    "id": 41,
    "name": "Lê Nguyễn Tuyết Anh",
    "tour": "Tà Năng - Phan Dũng",
    "date": "07/03/2026",
    "schedule_id": null,
    "status": "Hoàn thành"
  },
  {
    "id": 31,
    "name": "Nguyễn Vi Thiên Ái",
    "tour": "Tà Năng - Phan Dũng",
    "date": "30/04/2026",
    "schedule_id": 14,
    "status": "Đã cọc (Chờ đi)"
  },
  {
    "id": 40,
    "name": "Văn Ý Linh ",
    "tour": "Tà Năng - Phan Dũng",
    "date": "30/04/2026",
    "schedule_id": 14,
    "status": "Đã cọc (Chờ đi)"
  },
  {
    "id": 39,
    "name": "VÕ THỊ BẢO HƯƠNG",
    "tour": "Tà Năng - Phan Dũng",
    "date": "07/03/2026",
    "schedule_id": null,
    "status": "Hoàn thành"
  },
  {
    "id": 38,
    "name": "Hà Thị Phương Dung",
    "tour": "Tà Năng - Phan Dũng",
    "date": "07/03/2026",
    "schedule_id": null,
    "status": "Hoàn thành"
  },
  {
    "id": 37,
    "name": "Nguyễn Thị Kim Dung ",
    "tour": "Tà Năng - Phan Dũng",
    "date": "07/03/2026",
    "schedule_id": null,
    "status": "Hoàn thành"
  },
  {
    "id": 36,
    "name": "Huỳnh Thị Mơ",
    "tour": "Tà Năng - Phan Dũng",
    "date": "07/03/2026",
    "schedule_id": null,
    "status": "Hoàn thành"
  },
  {
    "id": 35,
    "name": "Nguyễn Hoàng Huy",
    "tour": "Tà Năng - Phan Dũng",
    "date": "07/03/2026",
    "schedule_id": null,
    "status": "Hoàn thành"
  },
  {
    "id": 57,
    "name": "Lưu Vĩnh Nghi",
    "tour": "Tà Năng - Phan Dũng",
    "date": "30/04/2026",
    "schedule_id": 14,
    "status": "Đã cọc (Chờ đi)"
  },
  {
    "id": 34,
    "name": "Châu Nguyệt Hân",
    "tour": "Tà Năng - Phan Dũng",
    "date": "30/04/2026",
    "schedule_id": 14,
    "status": "Đã cọc (Chờ đi)"
  },
  {
    "id": 33,
    "name": "Văn Thảo My",
    "tour": "Tà Năng - Phan Dũng",
    "date": "30/04/2026",
    "schedule_id": 14,
    "status": "Đã cọc (Chờ đi)"
  },
  {
    "id": 32,
    "name": "Nguyễn Khánh Quỳnh",
    "tour": "Tà Năng - Phan Dũng",
    "date": "30/04/2026",
    "schedule_id": 14,
    "status": "Đã cọc (Chờ đi)"
  },
  {
    "id": 59,
    "name": "Hồ Hửu Khánh",
    "tour": "Tà Năng - Phan Dũng",
    "date": "30/04/2026",
    "schedule_id": 14,
    "status": "Đã cọc (Chờ đi)"
  },
  {
    "id": 66,
    "name": "Hoàng Phủ Ngọc Diệp",
    "tour": "Tà Năng - Phan Dũng",
    "date": "07/03/2026",
    "schedule_id": null,
    "status": "Hoàn thành"
  },
  {
    "id": 348,
    "name": "Trần Thị Hiền Thảo",
    "tour": "Tà Năng - Phan Dũng",
    "date": "11/04/2026",
    "schedule_id": 30,
    "status": "Đã cọc (Chờ đi)"
  },
  {
    "id": 89,
    "name": "Lương Thị Mỹ Lệ",
    "tour": "Tà Năng - Phan Dũng",
    "date": "07/03/2026",
    "schedule_id": null,
    "status": "Hoàn thành"
  },
  {
    "id": 68,
    "name": "Nguyễn Phúc Gia Hưng",
    "tour": "Tà Năng - Phan Dũng",
    "date": "07/03/2026",
    "schedule_id": null,
    "status": "Hoàn thành"
  },
  {
    "id": 88,
    "name": "Nguyễn Ngọc Trâm Anh",
    "tour": "Tà Năng - Phan Dũng",
    "date": "07/03/2026",
    "schedule_id": null,
    "status": "Hoàn thành"
  },
  {
    "id": 91,
    "name": "Vũ Anh Kiệt",
    "tour": "Tà Năng - Phan Dũng",
    "date": "30/04/2026",
    "schedule_id": 14,
    "status": "Đã cọc (Chờ đi)"
  },
  {
    "id": 90,
    "name": "Vũ Ngọc Phương Như",
    "tour": "Tà Năng - Phan Dũng",
    "date": "07/03/2026",
    "schedule_id": null,
    "status": "Hoàn thành"
  },
  {
    "id": 67,
    "name": "NGUYỄN KIM NGÂN",
    "tour": "Tà Năng - Phan Dũng",
    "date": "07/03/2026",
    "schedule_id": null,
    "status": "Hoàn thành"
  },
  {
    "id": 101,
    "name": "Vũ Thị Phượng",
    "tour": "Tà Năng - Phan Dũng",
    "date": "07/03/2026",
    "schedule_id": null,
    "status": "Hoàn thành"
  },
  {
    "id": 108,
    "name": "NGUYỄN PHƯƠNG HIỀN",
    "tour": "Tà Năng - Phan Dũng",
    "date": "07/03/2026",
    "schedule_id": null,
    "status": "Hoàn thành"
  },
  {
    "id": 109,
    "name": "PHẠM KHẢ TÚ",
    "tour": "Tà Năng - Phan Dũng",
    "date": "07/03/2026",
    "schedule_id": null,
    "status": "Hoàn thành"
  },
  {
    "id": 350,
    "name": "Phan Ngọc Song Duyên",
    "tour": "Tà Năng - Phan Dũng",
    "date": "25/04/2026",
    "schedule_id": 32,
    "status": "Đã cọc (Chờ đi)"
  },
  {
    "id": 110,
    "name": "NGUYỄN THỊ THU HOÀI",
    "tour": "Tà Năng - Phan Dũng",
    "date": "07/03/2026",
    "schedule_id": null,
    "status": "Hoàn thành"
  },
  {
    "id": 233,
    "name": "Nguyễn Đăng Phúc Tiên",
    "tour": "Tà Năng - Phan Dũng",
    "date": "30/04/2026",
    "schedule_id": 14,
    "status": "Đã cọc (Chờ đi)"
  },
  {
    "id": 237,
    "name": "Trần Nguyễn Xuân Hương",
    "tour": "Tà Năng - Phan Dũng",
    "date": "30/04/2026",
    "schedule_id": 14,
    "status": "Đã cọc (Chờ đi)"
  },
  {
    "id": 229,
    "name": "Huỳnh Nguyễn Thanh Thảo",
    "tour": "Tà Năng - Phan Dũng",
    "date": "25/04/2026",
    "schedule_id": 23,
    "status": "Đã cọc (Chờ đi)"
  },
  {
    "id": 241,
    "name": "Phan Văn Hùng",
    "tour": "Tà Năng - Phan Dũng",
    "date": "30/04/2026",
    "schedule_id": 27,
    "status": "Đã cọc (Chờ đi)"
  },
  {
    "id": 93,
    "name": "Vũ Huy Phát",
    "tour": "Tà Năng - Phan Dũng",
    "date": "30/04/2026",
    "schedule_id": 14,
    "status": "Đã cọc (Chờ đi)"
  },
  {
    "id": 238,
    "name": "Nguyễn Ngọc Khánh Nhi",
    "tour": "Tà Năng - Phan Dũng",
    "date": "30/04/2026",
    "schedule_id": 14,
    "status": "Đã cọc (Chờ đi)"
  },
  {
    "id": 351,
    "name": "Trần Văn Thái",
    "tour": "Tà Năng - Phan Dũng",
    "date": "11/04/2026",
    "schedule_id": 30,
    "status": "Đã cọc (Chờ đi)"
  },
  {
    "id": 259,
    "name": "Lê Thị Anh Thư",
    "tour": "Tà Năng - Phan Dũng",
    "date": "21/03/2026",
    "schedule_id": 12,
    "status": "Hoàn tất"
  },
  {
    "id": 144,
    "name": "Nguyễn Quốc Khải ",
    "tour": "Tà Năng - Phan Dũng",
    "date": "25/04/2026",
    "schedule_id": null,
    "status": "Đã cọc"
  },
  {
    "id": 160,
    "name": "Lê Công Ngôi",
    "tour": "Tà Năng - Phan Dũng",
    "date": "30/04/2026",
    "schedule_id": 14,
    "status": "Đã cọc (Chờ đi)"
  },
  {
    "id": 145,
    "name": "Nguyễn Thị Thu Thảo",
    "tour": "Tà Năng - Phan Dũng",
    "date": "25/04/2026",
    "schedule_id": 23,
    "status": "Đã cọc (Chờ đi)"
  },
  {
    "id": 142,
    "name": "Võ Phạm Hoài Phú ",
    "tour": "Tà Năng - Phan Dũng",
    "date": "25/04/2026",
    "schedule_id": 23,
    "status": "Đã cọc (Chờ đi)"
  },
  {
    "id": 164,
    "name": "Trương Y Quỳnh",
    "tour": "Tà Năng - Phan Dũng",
    "date": "21/03/2026",
    "schedule_id": null,
    "status": "Hoàn tất"
  },
  {
    "id": 143,
    "name": "Hồ Lê Bảo Thoa",
    "tour": "Tà Năng - Phan Dũng",
    "date": "25/04/2026",
    "schedule_id": 23,
    "status": "Đã cọc (Chờ đi)"
  },
  {
    "id": 150,
    "name": "Nguyễn Ngọc Hoàng Yến",
    "tour": "Tà Năng - Phan Dũng",
    "date": "25/04/2026",
    "schedule_id": 23,
    "status": "Chờ xác nhận cọc"
  },
  {
    "id": 354,
    "name": "Trương Thanh Trầm",
    "tour": "Tà Năng - Phan Dũng",
    "date": "30/04/2026",
    "schedule_id": 27,
    "status": "Đã cọc (Chờ đi)"
  },
  {
    "id": 159,
    "name": "Đặng Trần Minh Khôi",
    "tour": "Tà Năng - Phan Dũng",
    "date": "30/04/2026",
    "schedule_id": 14,
    "status": "Đã cọc (Chờ đi)"
  },
  {
    "id": 172,
    "name": "Dương Thị Tuyết Nguyên",
    "tour": "Tà Năng - Phan Dũng",
    "date": "30/04/2026",
    "schedule_id": 14,
    "status": "Đã cọc (Chờ đi)"
  },
  {
    "id": 355,
    "name": "Tăng Thị Thuỳ Linh",
    "tour": "Tà Năng - Phan Dũng",
    "date": "2026-04-25",
    "schedule_id": null,
    "status": "Chờ xác nhận cọc"
  },
  {
    "id": 175,
    "name": "Huỳnh Thị Kim Hoa ",
    "tour": "Tà Năng - Phan Dũng",
    "date": "21/03/2026",
    "schedule_id": null,
    "status": "Hoàn tất"
  },
  {
    "id": 174,
    "name": "Võ Thị Thanh Nhàn",
    "tour": "Tà Năng - Phan Dũng",
    "date": "30/04/2026",
    "schedule_id": 14,
    "status": "Đã cọc (Chờ đi)"
  },
  {
    "id": 353,
    "name": "Nguyễn Thị Hà My",
    "tour": "Tà Năng - Phan Dũng",
    "date": "30/04/2026",
    "schedule_id": 27,
    "status": "Đã cọc (Chờ đi)"
  },
  {
    "id": 161,
    "name": "Nguyễn Lữ Minh Phương",
    "tour": "Tà Năng - Phan Dũng",
    "date": "25/04/2026",
    "schedule_id": 23,
    "status": "Đã cọc (Chờ đi)"
  },
  {
    "id": 177,
    "name": " Lê Thị Diễm My",
    "tour": "Tà Năng - Phan Dũng",
    "date": "30/04/2026",
    "schedule_id": 14,
    "status": "Đã cọc (Chờ đi)"
  },
  {
    "id": 170,
    "name": "Nguyễn Thị Huỳnh My",
    "tour": "Tà Năng - Phan Dũng",
    "date": "21/03/2026",
    "schedule_id": 12,
    "status": "Hoàn tất"
  },
  {
    "id": 176,
    "name": "Huỳnh Công Sang",
    "tour": "Tà Năng - Phan Dũng",
    "date": "21/03/2026",
    "schedule_id": null,
    "status": "Hoàn tất"
  },
  {
    "id": 248,
    "name": "Nguyễn Thị Ngọc Hà My",
    "tour": "Tà Năng - Phan Dũng",
    "date": "25/04/2026",
    "schedule_id": 23,
    "status": "Đã cọc (Chờ đi)"
  },
  {
    "id": 256,
    "name": "Nguyễn Thị Kim Ngân",
    "tour": "Tà Năng - Phan Dũng",
    "date": "30/04/2026",
    "schedule_id": 27,
    "status": "Đã cọc (Chờ đi)"
  },
  {
    "id": 239,
    "name": "Nguyễn Quang Minh",
    "tour": "Tà Năng - Phan Dũng",
    "date": "21/03/2026",
    "schedule_id": null,
    "status": "Hoàn tất"
  },
  {
    "id": 264,
    "name": "Trần Huỳnh Mỹ Hạnh",
    "tour": "Tà Năng - Phan Dũng",
    "date": "25/04/2026",
    "schedule_id": 23,
    "status": "Đã cọc (Chờ đi)"
  },
  {
    "id": 271,
    "name": "Huỳnh Phương Bảo Khánh",
    "tour": "Tà Năng - Phan Dũng",
    "date": "25/04/2026",
    "schedule_id": 23,
    "status": "Đã cọc (Chờ đi)"
  },
  {
    "id": 260,
    "name": "Trương Lê Minh Trí",
    "tour": "Tà Năng - Phan Dũng",
    "date": "21/03/2026",
    "schedule_id": 12,
    "status": "Hoàn tất"
  },
  {
    "id": 274,
    "name": "Nguyễn Hoàng Phúc",
    "tour": "Tà Năng - Phan Dũng",
    "date": "11/04/2026",
    "schedule_id": 30,
    "status": "Đã cọc (Chờ đi)"
  },
  {
    "id": 273,
    "name": "Phan Tú Uyên Nhi",
    "tour": "Tà Năng - Phan Dũng",
    "date": "11/04/2026",
    "schedule_id": 30,
    "status": "Đã cọc (Chờ đi)"
  },
  {
    "id": 356,
    "name": "Tăng Thị Thuỳ Linh",
    "tour": "Tà Năng - Phan Dũng",
    "date": "2026-04-25",
    "schedule_id": null,
    "status": "Đã cọc (Chờ đi)"
  },
  {
    "id": 357,
    "name": "Lê Tấn Phát",
    "tour": "Tà Năng - Phan Dũng",
    "date": "2026-04-25",
    "schedule_id": null,
    "status": "Đã cọc (Chờ đi)"
  },
  {
    "id": 371,
    "name": "Đinh Thị Tuyết Hồng",
    "tour": "Tà Năng - Phan Dũng",
    "date": "30/04/2026",
    "schedule_id": 27,
    "status": "Đã cọc (Chờ đi)"
  },
  {
    "id": 392,
    "name": "Trần Duy Khánh",
    "tour": "Tà Năng - Phan Dũng",
    "date": "25/04/2026",
    "schedule_id": 32,
    "status": "Đã cọc (Chờ đi)"
  },
  {
    "id": 393,
    "name": "Lưu Thị Yến Thuận",
    "tour": "Tà Năng - Phan Dũng",
    "date": "25/04/2026",
    "schedule_id": 32,
    "status": "Đã cọc (Chờ đi)"
  },
  {
    "id": 389,
    "name": "Nguyễn Thanh An",
    "tour": "Tà Năng - Phan Dũng",
    "date": "25/04/2026",
    "schedule_id": 32,
    "status": "Đã cọc (Chờ đi)"
  },
  {
    "id": 391,
    "name": "Nguyễn Thảo My",
    "tour": "Tà Năng - Phan Dũng",
    "date": "25/04/2026",
    "schedule_id": 32,
    "status": "Đã cọc (Chờ đi)"
  },
  {
    "id": 390,
    "name": "Nguyễn Thị Dung",
    "tour": "Tà Năng - Phan Dũng",
    "date": "2026-04-25",
    "schedule_id": null,
    "status": "Đã cọc (Chờ đi)"
  },
  {
    "id": 372,
    "name": "ĐẶNG THỊ THÙY TRANG",
    "tour": "Tà Năng - Phan Dũng",
    "date": "30/04/2026",
    "schedule_id": 27,
    "status": "Đã cọc (Chờ đi)"
  },
  {
    "id": 381,
    "name": "Nguyễn Thị Thu Hương",
    "tour": "Tà Năng - Phan Dũng",
    "date": "2026-04-25",
    "schedule_id": null,
    "status": "Đã cọc (Chờ đi)"
  },
  {
    "id": 293,
    "name": "Phạm Thị Xuân Thư",
    "tour": "Tà Năng - Phan Dũng",
    "date": "18/04/2026",
    "schedule_id": 28,
    "status": "Đã cọc (Chờ đi)"
  },
  {
    "id": 283,
    "name": "Thái Gia Hào",
    "tour": "Tà Năng - Phan Dũng",
    "date": "21/03/2026",
    "schedule_id": 12,
    "status": "Hoàn tất"
  },
  {
    "id": 279,
    "name": "Nguyễn Bảo Ly",
    "tour": "Tà Năng - Phan Dũng",
    "date": "25/04/2026",
    "schedule_id": 23,
    "status": "Đã cọc (Chờ đi)"
  },
  {
    "id": 289,
    "name": "Hồ Ngọc Thảo",
    "tour": "Tà Năng - Phan Dũng",
    "date": "30/04/2026",
    "schedule_id": 27,
    "status": "Đã cọc (Chờ đi)"
  },
  {
    "id": 290,
    "name": "Nguyễn Thị Kim Dung",
    "tour": "Tà Năng - Phan Dũng",
    "date": "30/04/2026",
    "schedule_id": 27,
    "status": "Đã cọc (Chờ đi)"
  },
  {
    "id": 280,
    "name": "Nguyễn Văn Thanh Long",
    "tour": "Tà Năng - Phan Dũng",
    "date": "21/03/2026",
    "schedule_id": 12,
    "status": "Hoàn thành"
  },
  {
    "id": 360,
    "name": "Hoàng Vũ Minh Thu",
    "tour": "Tà Năng - Phan Dũng",
    "date": "11/04/2026",
    "schedule_id": 30,
    "status": "Đã cọc (Chờ đi)"
  },
  {
    "id": 149,
    "name": "Đinh Thanh Phong",
    "tour": "Tà Năng - Phan Dũng",
    "date": "25/04/2026",
    "schedule_id": 23,
    "status": "Đã cọc (Chờ đi)"
  },
  {
    "id": 282,
    "name": "Nguyễn Hoàng Phúc",
    "tour": "Tà Năng - Phan Dũng",
    "date": "21/03/2026",
    "schedule_id": 12,
    "status": "Hoàn tất"
  },
  {
    "id": 361,
    "name": "Nguyễn Thị Kim Ngân",
    "tour": "Tà Năng - Phan Dũng",
    "date": "30/04/2026",
    "schedule_id": 27,
    "status": "Đã cọc (Chờ đi)"
  },
  {
    "id": 362,
    "name": "Hoàng Vũ Minh Thu",
    "tour": "Tà Năng - Phan Dũng",
    "date": "11/04/2026",
    "schedule_id": 30,
    "status": "Chờ cọc"
  },
  {
    "id": 363,
    "name": "Nguyễn Hữu Thảo My",
    "tour": "Tà Năng - Phan Dũng",
    "date": "11/04/2026",
    "schedule_id": 30,
    "status": "Đã cọc (Chờ đi)"
  },
  {
    "id": 370,
    "name": "Phạm Thị Ngọc Huyền",
    "tour": "Tà Năng - Phan Dũng",
    "date": "30/04/2026",
    "schedule_id": 27,
    "status": "Đã cọc (Chờ đi)"
  },
  {
    "id": 267,
    "name": "Trần Thị Thuỳ Trang",
    "tour": "Tà Năng - Phan Dũng",
    "date": "25/04/2026",
    "schedule_id": 23,
    "status": "Đã cọc (Chờ đi)"
  },
  {
    "id": 308,
    "name": "Đỗ Kim Phú Ngân",
    "tour": "Tà Năng - Phan Dũng",
    "date": "30/04/2026",
    "schedule_id": 27,
    "status": "Đã cọc (Chờ đi)"
  },
  {
    "id": 300,
    "name": "Nguyễn Bùi Thảo Ngân",
    "tour": "Tà Năng - Phan Dũng",
    "date": "30/04/2026",
    "schedule_id": 27,
    "status": "Chờ xác nhận cọc"
  },
  {
    "id": 304,
    "name": "Nguyễn Lâm Bảo Khánh",
    "tour": "Tà Năng - Phan Dũng",
    "date": "25/04/2026",
    "schedule_id": 32,
    "status": "Đã cọc (Chờ đi)"
  },
  {
    "id": 309,
    "name": "Nguyễn Thị Kiều Như",
    "tour": "Tà Năng - Phan Dũng",
    "date": "30/04/2026",
    "schedule_id": 27,
    "status": "Đã cọc (Chờ đi)"
  },
  {
    "id": 298,
    "name": "Võ Thị Thanh Ngôn",
    "tour": "Tà Năng - Phan Dũng",
    "date": "11/04/2026",
    "schedule_id": 30,
    "status": "Đã cọc (Chờ đi)"
  },
  {
    "id": 303,
    "name": "Đỗ Huỳnh Thanh Mẫn",
    "tour": "Tà Năng - Phan Dũng",
    "date": "25/04/2026",
    "schedule_id": 32,
    "status": "Đã cọc (Chờ đi)"
  },
  {
    "id": 299,
    "name": "Huỳnh Tôn Hưng",
    "tour": "Tà Năng - Phan Dũng",
    "date": "11/04/2026",
    "schedule_id": 30,
    "status": "Đã cọc (Chờ đi)"
  },
  {
    "id": 297,
    "name": "Võ Thị Yến Nhi",
    "tour": "Tà Năng - Phan Dũng",
    "date": "25/04/2026",
    "schedule_id": 23,
    "status": "Đã cọc (Chờ đi)"
  },
  {
    "id": 376,
    "name": "Nguyễn Thân Mỹ Lệ",
    "tour": "Tà Năng - Phan Dũng",
    "date": "",
    "schedule_id": null,
    "status": "Đã cọc (Chờ đi)"
  },
  {
    "id": 315,
    "name": "Trần Thị Hồng Liên ",
    "tour": "Tà Năng - Phan Dũng",
    "date": "25/04/2026",
    "schedule_id": 32,
    "status": "Đã cọc (Chờ đi)"
  },
  {
    "id": 310,
    "name": "Lê Thị Thuý Trinh",
    "tour": "Tà Năng - Phan Dũng",
    "date": "30/04/2026",
    "schedule_id": 27,
    "status": "Đã cọc (Chờ đi)"
  },
  {
    "id": 374,
    "name": "Phan Trần Thảo My",
    "tour": "Tà Năng - Phan Dũng",
    "date": "18/04/2026",
    "schedule_id": 28,
    "status": "Chờ cọc"
  },
  {
    "id": 387,
    "name": "Đặng Thị Đổ Quyên",
    "tour": "Tà Năng - Phan Dũng",
    "date": "18/04/2026",
    "schedule_id": 28,
    "status": "Đã cọc (Chờ đi)"
  },
  {
    "id": 388,
    "name": "Trương Thị Xuân Hào",
    "tour": "Tà Năng - Phan Dũng",
    "date": "18/04/2026",
    "schedule_id": 28,
    "status": "Đã cọc (Chờ đi)"
  },
  {
    "id": 325,
    "name": "Phạm Quỳnh Lan Anh ",
    "tour": "Tà Năng - Phan Dũng",
    "date": "18/04/2026",
    "schedule_id": 28,
    "status": "Đã cọc (Chờ đi)"
  },
  {
    "id": 146,
    "name": "Nguyễn Xuân Tường Huy",
    "tour": "Tà Năng - Phan Dũng",
    "date": "25/04/2026",
    "schedule_id": 23,
    "status": "Đã cọc (Chờ đi)"
  },
  {
    "id": 332,
    "name": "Nguyễn Thị Phượng Uyển",
    "tour": "Tà Năng - Phan Dũng",
    "date": "25/04/2026",
    "schedule_id": 23,
    "status": "Đã cọc (Chờ đi)"
  },
  {
    "id": 327,
    "name": "Vũ Hoàng Tuyết Nhi",
    "tour": "Tà Năng - Phan Dũng",
    "date": "25/04/2026",
    "schedule_id": 32,
    "status": "Đã cọc (Chờ đi)"
  },
  {
    "id": 326,
    "name": "Nguyễn Thị Dung ",
    "tour": "Tà Năng - Phan Dũng",
    "date": "25/04/2026",
    "schedule_id": 32,
    "status": "Đã cọc (Chờ đi)"
  },
  {
    "id": 335,
    "name": "Nguyễn Thị Châu Đoan",
    "tour": "Tà Năng - Phan Dũng",
    "date": "25/04/2026",
    "schedule_id": 23,
    "status": "Đã cọc (Chờ đi)"
  },
  {
    "id": 328,
    "name": "Huỳnh Võ Anh Kiệt",
    "tour": "Tà Năng - Phan Dũng",
    "date": "11/04/2026",
    "schedule_id": 30,
    "status": "Đã cọc (Chờ đi)"
  },
  {
    "id": 375,
    "name": "Nguyễn Duy Anh",
    "tour": "Tà Năng - Phan Dũng",
    "date": "2026-04-25",
    "schedule_id": null,
    "status": "Chờ xác nhận cọc"
  },
  {
    "id": 338,
    "name": "Mai Thị Thanh",
    "tour": "Tà Năng - Phan Dũng",
    "date": "30/04/2026",
    "schedule_id": 14,
    "status": "Đã cọc (Chờ đi)"
  },
  {
    "id": 288,
    "name": "Võ Trần Nguyên Khang",
    "tour": "Tà Năng - Phan Dũng",
    "date": "18/04/2026",
    "schedule_id": 28,
    "status": "Đã cọc (Chờ đi)"
  },
  {
    "id": 330,
    "name": "Nguyễn Huỳnh Anh Trúc",
    "tour": "Tà Năng - Phan Dũng",
    "date": "30/04/2026",
    "schedule_id": 27,
    "status": "Đã cọc (Chờ đi)"
  },
  {
    "id": 384,
    "name": "Nguyễn Thị Hoàng Giang",
    "tour": "Tà Năng - Phan Dũng",
    "date": "25/04/2026",
    "schedule_id": 32,
    "status": "Chờ cọc"
  },
  {
    "id": 385,
    "name": "Nguyễn Thị Hoàng Trang",
    "tour": "Tà Năng - Phan Dũng",
    "date": "25/04/2026",
    "schedule_id": 32,
    "status": "Chờ cọc"
  },
  {
    "id": 346,
    "name": "Lê Hải Dương",
    "tour": "Tà Năng - Phan Dũng",
    "date": "25/04/2026",
    "schedule_id": 32,
    "status": "Đã cọc (Chờ đi)"
  },
  {
    "id": 386,
    "name": "Nguyễn Thị Thục Nhi",
    "tour": "Tà Năng - Phan Dũng",
    "date": "25/04/2026",
    "schedule_id": 32,
    "status": "Đã cọc (Chờ đi)"
  },
  {
    "id": 345,
    "name": "Tường Minh Hoàng",
    "tour": "Tà Năng - Phan Dũng",
    "date": "25/04/2026",
    "schedule_id": 32,
    "status": "Đã cọc (Chờ đi)"
  },
  {
    "id": 336,
    "name": "Nguyễn Hoài Bảo",
    "tour": "Tà Năng - Phan Dũng",
    "date": "25/04/2026",
    "schedule_id": 23,
    "status": "Đã cọc (Chờ đi)"
  }
]